pract_1/decoder_2.vhdl
library IEEE;
use IEEE.std_logic_1164.all;
use IEEE.numeric_std.all;

entity decoder_2 is 
    port (
        a: in std_ulogic;
        b: in std_ulogic;
        e: in std_ulogic;
        q: out std_logic_vector(3 downto 0)
    );
end decoder_2 ;

architecture bhv of decoder_2 is
begin 
    q(0) <= e and ((not a) and (not b));
    q(1) <= e and (a and (not b));
    q(2) <= e and ((not a) and b);
    q(3) <= e and (a and b);
end bhv;

pract_1/decoder_3.vhdl
library IEEE;
use IEEE.std_logic_1164.all;
use IEEE.numeric_std.all;

entity decoder_3 is 
    port (
        d3_a: in std_ulogic;
        d3_b: in std_ulogic;
        d3_c: in std_ulogic;
        d3_e: in std_ulogic;
        d3_q: out std_logic_vector(7 downto 0)
    );
end decoder_3;

architecture bhv of decoder_3 is
    component decoder_2 
        port (
            a: in std_ulogic;
            b: in std_ulogic;
            e: in std_ulogic;
            q: out std_logic_vector(3 downto 0)
        );
    end component;

    -- signal dec2_e: std_ulogic;
    signal X1 : std_logic_vector(3 downto 0);

begin 
    decode_map : decoder_2 port map (a => d3_a, b => d3_b, e => d3_e, q(3 downto 0) => X1(3 downto 0));
    
    -- dec2_e <= '1';

    d3_q(0) <= d3_e and (X1(0) and (not d3_c));
    d3_q(1) <= d3_e and (X1(1) and (not d3_c));
    d3_q(2) <= d3_e and (X1(2) and (not d3_c));
    d3_q(3) <= d3_e and (X1(3) and (not d3_c));
    
    d3_q(4) <= d3_e and (X1(0) and d3_c);
    d3_q(5) <= d3_e and (X1(1) and d3_c);
    d3_q(6) <= d3_e and (X1(2) and d3_c);
    d3_q(7) <= d3_e and (X1(3) and d3_c);

end bhv;

pract_1/decoder_3_tb.vhdl
library IEEE;
use IEEE.std_logic_1164.all;
use IEEE.numeric_std.all;

entity decoder_3_tb is 
end decoder_3_tb;

architecture test of decoder_3_tb is
    component decoder_3 
        port (
            d3_a: in std_ulogic;
            d3_b: in std_ulogic;
            d3_c: in std_ulogic;
            d3_e: in std_ulogic;
            d3_q: out std_logic_vector(7 downto 0)
        );
    end component;

    signal a, b, c, e : std_ulogic;
    signal q : std_logic_vector(7 downto 0);

begin 
    decode_map : decoder_3 port map (d3_a => a, d3_b => b, d3_c => c, d3_e => e, d3_q(7 downto 0) => q(7 downto 0));
    process  begin
        
        e <= '0';
        a <= '0';
        b <= '0';
        c <= '0';
        wait for 1 ns;

        e <= '1';
        a <= '0';
        b <= '0';
        c <= '0';
        wait for 1 ns;

        a <= '1';
        b <= '0';
        c <= '0';
        wait for 1 ns;

        a <= '0';
        b <= '1';
        c <= '0';
        wait for 1 ns;

        a <= '1';
        b <= '1';
        c <= '0';
        wait for 1 ns;

        -- c = 1 
        a <= '0';
        b <= '0';
        c <= '1';
        wait for 1 ns;

        a <= '1';
        b <= '0';
        wait for 1 ns;

        a <= '0';
        b <= '1';
        wait for 1 ns;

        a <= '1';
        b <= '1';
        wait for 1 ns;

        assert false report "reached end of tests!";
        wait;
    end process;

end test;

pract_1/export/decoder_3_tb.vcd
$date
  Thu Sep 21 17:07:53 2023
$end
$version
  GHDL v0
$end
$timescale
  1 fs
$end
$scope module standard $end
$upscope $end
$scope module std_logic_1164 $end
$upscope $end
$scope module numeric_std $end
$upscope $end
$scope module decoder_3_tb $end
$var reg 1 ! a $end
$var reg 1 " b $end
$var reg 1 # c $end
$var reg 1 $ e $end
$var reg 8 % q[7:0] $end
$scope module decode_map $end
$var reg 1 & d3_a $end
$var reg 1 ' d3_b $end
$var reg 1 ( d3_c $end
$var reg 1 ) d3_e $end
$var reg 8 * d3_q[7:0] $end
$var reg 4 + x1[3:0] $end
$scope module decode_map $end
$var reg 1 , a $end
$var reg 1 - b $end
$var reg 1 . e $end
$var reg 4 / q[3:0] $end
$upscope $end
$upscope $end
$upscope $end
$enddefinitions $end
#0
0!
0"
0#
0$
b00000000 %
0&
0'
0(
0)
b00000000 *
b0000 +
0,
0-
0.
b0000 /
#1000000
1$
b00000001 %
1)
b00000001 *
b0001 +
1.
b0001 /
#2000000
1!
b00000010 %
1&
b00000010 *
b0010 +
1,
b0010 /
#3000000
0!
1"
b00000100 %
0&
1'
b00000100 *
b0100 +
0,
1-
b0100 /
#4000000
1!
b00001000 %
1&
b00001000 *
b1000 +
1,
b1000 /
#5000000
0!
0"
1#
b00010000 %
0&
0'
1(
b00010000 *
b0001 +
0,
0-
b0001 /
#6000000
1!
b00100000 %
1&
b00100000 *
b0010 +
1,
b0010 /
#7000000
0!
1"
b01000000 %
0&
1'
b01000000 *
b0100 +
0,
1-
b0100 /
#8000000
1!
b10000000 %
1&
b10000000 *
b1000 +
1,
b1000 /
